{
    "batch_size": {
      "_type": "choice",
      "_value": [
        2,4,8,16,32,64,128,256,512,1024
      ]
    },
    "learning_rate": {
      "_type": "choice",
      "_value": [
        0.01,0.001,0.0001,0.00001,0.000001
      ]
    },
    "fine_tune": {
      "_type": "choice",
      "_value": [
        0,1,2,3,4,5,6,7,8,9,10
      ]
    },
    "class_weights": {
        "_type": "choice",
        "_value": [
          true,false
        ]
      },
      "model_name": {
        "_type": "choice",
        "_value": [
            "VGG16","mobile_net","conv"
        ]
      },
      "preprocessing_function": {
        "_type": "choice",
        "_value": [
            true,false
        ]
      }
  }